gene4mVCF/__init__.py
gene4mVCF/fetchgenes.py
gene4mVCF-1.1.5.dist-info/METADATA
gene4mVCF-1.1.5.dist-info/WHEEL
gene4mVCF-1.1.5.dist-info/entry_points.txt
gene4mVCF-1.1.5.dist-info/top_level.txt
gene4mVCF-1.1.5.dist-info/RECORD
