Metadata-Version: 2.1
Name: gene4mVCF
Version: 1.1.5
Summary: Description of your package
Home-page: https://github.com/vkulaganathan/gene4mVCF
Author: Pr (France). Dr. rer. nat. Vijay K. ULAGANATHAN
Author-email: vijay-kumar.ulaganathan@uni-tuebingen.de
Requires-Dist: pysam >=0.16.0.1
Requires-Dist: pandas >=1.0.0
Requires-Dist: pybedtools >=0.8.0
Requires-Dist: tqdm >=4.47.0
Requires-Dist: gffutils >=0.10.1
